{
	"name": "ETL_GOLD",
	"properties": {
		"activities": [
			{
				"name": "Data flow1",
				"type": "ExecuteDataFlow",
				"dependsOn": [
					{
						"activity": "Data flow11",
						"dependencyConditions": [
							"Succeeded"
						]
					}
				],
				"policy": {
					"timeout": "0.12:00:00",
					"retry": 0,
					"retryIntervalInSeconds": 30,
					"secureOutput": false,
					"secureInput": false
				},
				"userProperties": [],
				"typeProperties": {
					"dataflow": {
						"referenceName": "gold_df_dim_ctry",
						"type": "DataFlowReference"
					},
					"compute": {
						"coreCount": 8,
						"computeType": "General"
					},
					"traceLevel": "Fine"
				}
			},
			{
				"name": "Data flow2",
				"type": "ExecuteDataFlow",
				"dependsOn": [
					{
						"activity": "Data flow1",
						"dependencyConditions": [
							"Succeeded"
						]
					}
				],
				"policy": {
					"timeout": "0.12:00:00",
					"retry": 0,
					"retryIntervalInSeconds": 30,
					"secureOutput": false,
					"secureInput": false
				},
				"userProperties": [],
				"typeProperties": {
					"dataflow": {
						"referenceName": "gold_df_dim_date",
						"type": "DataFlowReference"
					},
					"compute": {
						"coreCount": 8,
						"computeType": "General"
					},
					"traceLevel": "Fine"
				}
			},
			{
				"name": "Data flow3",
				"type": "ExecuteDataFlow",
				"dependsOn": [
					{
						"activity": "Data flow2",
						"dependencyConditions": [
							"Succeeded"
						]
					}
				],
				"policy": {
					"timeout": "0.12:00:00",
					"retry": 0,
					"retryIntervalInSeconds": 30,
					"secureOutput": false,
					"secureInput": false
				},
				"userProperties": [],
				"typeProperties": {
					"dataflow": {
						"referenceName": "gold_df_dim_gnr",
						"type": "DataFlowReference"
					},
					"compute": {
						"coreCount": 8,
						"computeType": "General"
					},
					"traceLevel": "Fine"
				}
			},
			{
				"name": "Data flow4",
				"type": "ExecuteDataFlow",
				"dependsOn": [
					{
						"activity": "Data flow3",
						"dependencyConditions": [
							"Succeeded"
						]
					}
				],
				"policy": {
					"timeout": "0.12:00:00",
					"retry": 0,
					"retryIntervalInSeconds": 30,
					"secureOutput": false,
					"secureInput": false
				},
				"userProperties": [],
				"typeProperties": {
					"dataflow": {
						"referenceName": "gold_df_dim_key_ven",
						"type": "DataFlowReference"
					},
					"compute": {
						"coreCount": 8,
						"computeType": "General"
					},
					"traceLevel": "Fine"
				}
			},
			{
				"name": "Data flow5",
				"type": "ExecuteDataFlow",
				"dependsOn": [
					{
						"activity": "Data flow4",
						"dependencyConditions": [
							"Succeeded"
						]
					}
				],
				"policy": {
					"timeout": "0.12:00:00",
					"retry": 0,
					"retryIntervalInSeconds": 30,
					"secureOutput": false,
					"secureInput": false
				},
				"userProperties": [],
				"typeProperties": {
					"dataflow": {
						"referenceName": "gold_df_mari_sta",
						"type": "DataFlowReference"
					},
					"compute": {
						"coreCount": 8,
						"computeType": "General"
					},
					"traceLevel": "Fine"
				}
			},
			{
				"name": "Data flow6",
				"type": "ExecuteDataFlow",
				"dependsOn": [
					{
						"activity": "Data flow5",
						"dependencyConditions": [
							"Succeeded"
						]
					}
				],
				"policy": {
					"timeout": "0.12:00:00",
					"retry": 0,
					"retryIntervalInSeconds": 30,
					"secureOutput": false,
					"secureInput": false
				},
				"userProperties": [],
				"typeProperties": {
					"dataflow": {
						"referenceName": "gold_df_dim_clientes",
						"type": "DataFlowReference"
					},
					"compute": {
						"coreCount": 8,
						"computeType": "General"
					},
					"traceLevel": "Fine"
				}
			},
			{
				"name": "Data flow7",
				"type": "ExecuteDataFlow",
				"dependsOn": [
					{
						"activity": "Data flow6",
						"dependencyConditions": [
							"Succeeded"
						]
					}
				],
				"policy": {
					"timeout": "0.12:00:00",
					"retry": 0,
					"retryIntervalInSeconds": 30,
					"secureOutput": false,
					"secureInput": false
				},
				"userProperties": [],
				"typeProperties": {
					"dataflow": {
						"referenceName": "gold_df_dim_productos_cat",
						"type": "DataFlowReference"
					},
					"compute": {
						"coreCount": 8,
						"computeType": "General"
					},
					"traceLevel": "Fine"
				}
			},
			{
				"name": "Data flow8",
				"type": "ExecuteDataFlow",
				"dependsOn": [
					{
						"activity": "Data flow7",
						"dependencyConditions": [
							"Succeeded"
						]
					}
				],
				"policy": {
					"timeout": "0.12:00:00",
					"retry": 0,
					"retryIntervalInSeconds": 30,
					"secureOutput": false,
					"secureInput": false
				},
				"userProperties": [],
				"typeProperties": {
					"dataflow": {
						"referenceName": "gold_df_dim_date_hdv",
						"type": "DataFlowReference"
					},
					"compute": {
						"coreCount": 8,
						"computeType": "General"
					},
					"traceLevel": "Fine"
				}
			},
			{
				"name": "Data flow9",
				"type": "ExecuteDataFlow",
				"dependsOn": [
					{
						"activity": "Data flow8",
						"dependencyConditions": [
							"Succeeded"
						]
					}
				],
				"policy": {
					"timeout": "0.12:00:00",
					"retry": 0,
					"retryIntervalInSeconds": 30,
					"secureOutput": false,
					"secureInput": false
				},
				"userProperties": [],
				"typeProperties": {
					"dataflow": {
						"referenceName": "gold_df_dim_productos",
						"type": "DataFlowReference"
					},
					"compute": {
						"coreCount": 8,
						"computeType": "General"
					},
					"traceLevel": "Fine"
				}
			},
			{
				"name": "Data flow10",
				"type": "ExecuteDataFlow",
				"dependsOn": [
					{
						"activity": "Data flow9",
						"dependencyConditions": [
							"Succeeded"
						]
					}
				],
				"policy": {
					"timeout": "0.12:00:00",
					"retry": 0,
					"retryIntervalInSeconds": 30,
					"secureOutput": false,
					"secureInput": false
				},
				"userProperties": [],
				"typeProperties": {
					"dataflow": {
						"referenceName": "gold_df_hechos_detalle_ventas",
						"type": "DataFlowReference"
					},
					"compute": {
						"coreCount": 8,
						"computeType": "General"
					},
					"traceLevel": "Fine"
				}
			},
			{
				"name": "Data flow11",
				"type": "ExecuteDataFlow",
				"dependsOn": [],
				"policy": {
					"timeout": "0.12:00:00",
					"retry": 0,
					"retryIntervalInSeconds": 30,
					"secureOutput": false,
					"secureInput": false
				},
				"userProperties": [],
				"typeProperties": {
					"dataflow": {
						"referenceName": "gold_df_dim_key_cat",
						"type": "DataFlowReference"
					},
					"compute": {
						"coreCount": 8,
						"computeType": "General"
					},
					"traceLevel": "Fine"
				}
			}
		],
		"folder": {
			"name": "ETL"
		},
		"annotations": []
	}
}